peewee_simple_migrate.py
peewee_simple_migrate-0.0.5.dist-info/DESCRIPTION.rst
peewee_simple_migrate-0.0.5.dist-info/METADATA
peewee_simple_migrate-0.0.5.dist-info/RECORD
peewee_simple_migrate-0.0.5.dist-info/WHEEL
peewee_simple_migrate-0.0.5.dist-info/metadata.json
peewee_simple_migrate-0.0.5.dist-info/top_level.txt
