Metadata-Version: 2.0
Name: peewee-simple-migrate
Version: 0.0.5
Summary: a simple migrations manager for peewee
Home-page: https://github.com/anjianshi/peewee-simple-migrate
Author: anjianshi
Author-email: anjianshi@gmail.com
License: MIT
Platform: UNKNOWN
Classifier: Intended Audience :: Developers
Classifier: License :: OSI Approved :: MIT License
Classifier: Operating System :: OS Independent
Classifier: Programming Language :: Python
Classifier: Programming Language :: Python :: 3
Requires-Dist: peewee
